toml_cli/__init__.py
toml_cli-0.8.2.dist-info/METADATA
toml_cli-0.8.2.dist-info/WHEEL
toml_cli-0.8.2.dist-info/entry_points.txt
toml_cli-0.8.2.dist-info/licenses/LICENSE
toml_cli-0.8.2.dist-info/RECORD
