Metadata-Version: 2.4
Name: toml-cli
Version: 0.8.2
Summary: Command line interface to read and write keys/values to/from toml files
Project-URL: Repository, https://github.com/mrijken/toml-cli
Author-email: Marc Rijken <marc@rijken.org>
License-Expression: MIT AND (Apache-2.0 OR BSD-2-Clause)
License-File: LICENSE
Requires-Python: >=3.10
Requires-Dist: jmespath>=1.0.1
Requires-Dist: regex>=2020.7.14
Requires-Dist: tomlkit>=0.13.3
Requires-Dist: typer>=0.16.0
